<?xml version="1.0" ?>
<scheme name="GruvboxLightHard" version="142" parent_scheme="Default">
  <colors>
    <option name="BACKGROUND" value="#F8F4D6"/>
    <option name="FOREGROUND" value="#282828"/>
    <option name="CARET_COLOR" value="#282828"/>
    <option name="SELECTION_BACKGROUND" value="#D5C4A1"/>
    <option name="SELECTION_FOREGROUND" value="#665C54"/>
    <option name="LINE_NUMBERS_COLOR" value="#000000"/>
    <option name="GUTTER_BACKGROUND" value="#F8F4D6"/>
  </colors>
  <attributes>
    <option name="DEFAULT_KEYWORD">
      <value>
        <option name="FOREGROUND" value="8F3F71"/>
      </value>
    </option>
    <option name="DEFAULT_STRING">
      <value>
        <option name="FOREGROUND" value="79740E"/>
      </value>
    </option>
    <option name="DEFAULT_NUMBER">
      <value>
        <option name="FOREGROUND" value="9D0006"/>
      </value>
    </option>
    <option name="DEFAULT_COMMENT">
      <value>
        <option name="FOREGROUND" value="9D8374"/>
      </value>
    </option>
    <option name="DEFAULT_IDENTIFIER">
      <value>
        <option name="FOREGROUND" value="282828"/>
      </value>
    </option>
    <option name="DEFAULT_FUNCTION_DECLARATION">
      <value>
        <option name="FOREGROUND" value="076678"/>
      </value>
    </option>
    <option name="DEFAULT_CLASS_NAME">
      <value>
        <option name="FOREGROUND" value="B57614"/>
      </value>
    </option>
    <option name="DEFAULT_CONSTANT">
      <value>
        <option name="FOREGROUND" value="427B58"/>
      </value>
    </option>
  </attributes>
</scheme>
