{
  "name": "Forestblue",
  "dark": true,
  "author": "Ghostty Converter",
  "editorScheme": "/ForestBlue.xml",
  "colors": {
    "primaryBackground": "#051519",
    "primaryForeground": "#e2d8cd",
    "selectionBackground": "#4d4d4d",
    "selectionForeground": "#ffffff"
  },
  "ui": {
    "*": {
      "background": "#051519",
      "foreground": "#e2d8cd"
    },
    "Panel.background": "#0a2a32",
    "Menu.background": "#0a2a32",
    "MenuBar.background": "#051519",
    "ToolWindow.background": "#0a2a32",
    "Editor.background": "#051519",
    "EditorTabs.background": "#0a2a32",
    "Tree.background": "#051519",
    "List.background": "#051519",
    "Table.background": "#051519",
    "TextField.background": "#051519",
    "Button.background": "#0a2a32",
    "Button.foreground": "#e2d8cd",
    "Button.hoverBackground": "#0c353f",
    "Button.pressedBackground": "#000000",
    "Component.borderColor": "#0f3f4c",
    "Component.focusedBorderColor": "#8ed0ce",
    "Component.disabledForeground": "#7b7670",
    "Link.activeForeground": "#8ed0ce",
    "Link.hoverForeground": "#8ed0ce",
    "Link.pressedForeground": "#8ed0ce",
    "Label.disabledForeground": "#7b7670",
    "Separator.foreground": "#0f3f4c",
    "TabbedPane.tabSelectionHeight": 2,
    "StatusBar.background": "#0a2a32",
    "ProgressBar.progressColor": "#8ed0ce",
    "ScrollBar.thumbColor": "#145565",
    "SearchEverywhere.background": "#0a2a32",
    "Notification.background": "#0a2a32",
    "Notification.errorBackground": "#1d1f24",
    "Notification.warningBackground": "#072120",
    "ValidationTooltip.errorBackground": "#f8818e",
    "ValidationTooltip.warningBackground": "#1a8e63"
  }
}