<?xml version="1.0" ?>
<scheme name="FrontEndDelight" version="142" parent_scheme="Darcula">
  <colors>
    <option name="BACKGROUND" value="#1B1C1D"/>
    <option name="FOREGROUND" value="#ADADAD"/>
    <option name="CARET_COLOR" value="#CDCDCD"/>
    <option name="SELECTION_BACKGROUND" value="#EA6154"/>
    <option name="SELECTION_FOREGROUND" value="#1B1C1D"/>
    <option name="LINE_NUMBERS_COLOR" value="#606060"/>
    <option name="GUTTER_BACKGROUND" value="#1B1C1D"/>
  </colors>
  <attributes>
    <option name="DEFAULT_KEYWORD">
      <value>
        <option name="FOREGROUND" value="F02E4F"/>
      </value>
    </option>
    <option name="DEFAULT_STRING">
      <value>
        <option name="FOREGROUND" value="565747"/>
      </value>
    </option>
    <option name="DEFAULT_NUMBER">
      <value>
        <option name="FOREGROUND" value="F8511B"/>
      </value>
    </option>
    <option name="DEFAULT_COMMENT">
      <value>
        <option name="FOREGROUND" value="5FAC6D"/>
      </value>
    </option>
    <option name="DEFAULT_IDENTIFIER">
      <value>
        <option name="FOREGROUND" value="ADADAD"/>
      </value>
    </option>
    <option name="DEFAULT_FUNCTION_DECLARATION">
      <value>
        <option name="FOREGROUND" value="2C70B7"/>
      </value>
    </option>
    <option name="DEFAULT_CLASS_NAME">
      <value>
        <option name="FOREGROUND" value="FA771D"/>
      </value>
    </option>
    <option name="DEFAULT_CONSTANT">
      <value>
        <option name="FOREGROUND" value="3CA1A6"/>
      </value>
    </option>
  </attributes>
</scheme>
